AetherX/__init__.py
AetherX-0.4.dist-info/LICENSE
AetherX-0.4.dist-info/METADATA
AetherX-0.4.dist-info/WHEEL
AetherX-0.4.dist-info/top_level.txt
AetherX-0.4.dist-info/zip-safe
AetherX-0.4.dist-info/RECORD
