Metadata-Version: 2.1
Name: AetherX
Version: 0.4
Summary: The AetherScript Programming Language
Home-page: https://github.com/ProjectDragonRealms/AetherScript
Author: Realms
Author-email: dragonrealms2008@gmail.com
License: MIT
Classifier: Programming Language :: Python
Classifier: Programming Language :: Python :: 3
Classifier: Topic :: Software Development :: Libraries
Classifier: Topic :: Software Development :: Libraries :: Python Modules
License-File: LICENSE
